xai_cola/__init__.py
xai_cola/version.py
xai_cola/ce_generator/__init__.py
xai_cola/ce_generator/auxiliary.py
xai_cola/ce_generator/base_explainer.py
xai_cola/ce_generator/dice.py
xai_cola/ce_generator/discount.py
xai_cola/ce_sparsifier/__init__.py
xai_cola/ce_sparsifier/cola.py
xai_cola/ce_sparsifier/data/__init__.py
xai_cola/ce_sparsifier/data/coladata.py
xai_cola/ce_sparsifier/models/__init__.py
xai_cola/ce_sparsifier/models/base.py
xai_cola/ce_sparsifier/models/factory.py
xai_cola/ce_sparsifier/models/pytorch.py
xai_cola/ce_sparsifier/models/sklearn.py
xai_cola/ce_sparsifier/models/tensorflow1.py
xai_cola/ce_sparsifier/models/tensorflow2.py
xai_cola/ce_sparsifier/policies/__init__.py
xai_cola/ce_sparsifier/policies/data_composer/__init__.py
xai_cola/ce_sparsifier/policies/data_composer/data_composer.py
xai_cola/ce_sparsifier/policies/feature_attributor/__init__.py
xai_cola/ce_sparsifier/policies/feature_attributor/base_attributor.py
xai_cola/ce_sparsifier/policies/feature_attributor/pshap.py
xai_cola/ce_sparsifier/policies/matching/__init__.py
xai_cola/ce_sparsifier/policies/matching/base_matcher.py
xai_cola/ce_sparsifier/policies/matching/cem_matcher.py
xai_cola/ce_sparsifier/policies/matching/ect_matcher.py
xai_cola/ce_sparsifier/policies/matching/nn_matcher.py
xai_cola/ce_sparsifier/policies/matching/ot_matcher.py
xai_cola/ce_sparsifier/utils/__init__.py
xai_cola/ce_sparsifier/utils/logger_config.py
xai_cola/ce_sparsifier/utils/preprocessor_wrapper.py
xai_cola/ce_sparsifier/utils/pytorch_models.py
xai_cola/ce_sparsifier/utils/warnings.py
xai_cola/ce_sparsifier/visualization/__init__.py
xai_cola/ce_sparsifier/visualization/diversity.py
xai_cola/ce_sparsifier/visualization/heatmap.py
xai_cola/ce_sparsifier/visualization/heatmap_direction.py
xai_cola/ce_sparsifier/visualization/highlight_dataframe.py
xai_cola/ce_sparsifier/visualization/stacked_bar.py
xai_cola/datasets/__init__.py
xai_cola/datasets/german_credit.py
xai_cola/datasets/rawdata/german_credit.csv
xai_cola-0.1.0.dist-info/licenses/LICENSE
xai_cola-0.1.0.dist-info/METADATA
xai_cola-0.1.0.dist-info/WHEEL
xai_cola-0.1.0.dist-info/top_level.txt
xai_cola-0.1.0.dist-info/RECORD
