Metadata-Version: 2.4
Name: xai-cola
Version: 0.1.0
Summary: COunterfactual explanations with Limited Actions (COLA)
Home-page: https://github.com/understanding-ml/COLA
Author: Lin Zhu, Lei You
Author-email: Lin Zhu <s232291@student.dtu.dk>, Lei You <leiyo@dtu.dk>
License: MIT
Project-URL: Homepage, https://github.com/understanding-ml/COLA
Project-URL: Documentation, https://cola.readthedocs.io/
Project-URL: Repository, https://github.com/understanding-ml/COLA
Project-URL: Issues, https://github.com/understanding-ml/COLA/issues
Keywords: explainable AI,XAI,counterfactual explanations,machine learning,interpretability
Classifier: Development Status :: 3 - Alpha
Classifier: Intended Audience :: Developers
Classifier: Intended Audience :: Science/Research
Classifier: License :: OSI Approved :: MIT License
Classifier: Programming Language :: Python :: 3
Classifier: Programming Language :: Python :: 3.9
Classifier: Programming Language :: Python :: 3.10
Classifier: Programming Language :: Python :: 3.11
Classifier: Programming Language :: Python :: 3.12
Classifier: Operating System :: OS Independent
Classifier: Operating System :: MacOS
Classifier: Operating System :: POSIX :: Linux
Classifier: Operating System :: Microsoft :: Windows
Classifier: Topic :: Scientific/Engineering :: Artificial Intelligence
Classifier: Topic :: Software Development :: Libraries :: Python Modules
Requires-Python: >=3.9
License-File: LICENSE
Requires-Dist: numpy<2.0,>=1.26.4
Requires-Dist: pandas<=2.3.0,>=2.0.0
Requires-Dist: scikit-learn<=1.7.0,>=1.3.0
Requires-Dist: scipy<=1.16.0,>=1.13.0
Requires-Dist: dice-ml<=0.12,>=0.10
Requires-Dist: cem==1.1.0
Requires-Dist: matplotlib>=3.8.0
Requires-Dist: seaborn>=0.13.0
Requires-Dist: shap>=0.41.0
Requires-Dist: POT>=0.9.0
Requires-Dist: torch>=2.3.0
Requires-Dist: tqdm>=4.67.0
Requires-Dist: ipython>=8.0.0
Provides-Extra: jupyter
Requires-Dist: ipython>=8.0.0; extra == "jupyter"
Requires-Dist: jupyter>=1.0.0; extra == "jupyter"
Requires-Dist: notebook>=6.0.0; extra == "jupyter"
Provides-Extra: all
Requires-Dist: xai-cola[jupyter]; extra == "all"
Provides-Extra: dev
Requires-Dist: pytest>=7.0; extra == "dev"
Requires-Dist: pytest-cov>=4.0; extra == "dev"
Requires-Dist: black>=23.0; extra == "dev"
Requires-Dist: flake8>=6.0; extra == "dev"
Requires-Dist: mypy>=1.0; extra == "dev"
Provides-Extra: docs
Requires-Dist: sphinx>=5.0; extra == "docs"
Requires-Dist: sphinx-rtd-theme>=1.0; extra == "docs"
Requires-Dist: furo>=2023.3.27; extra == "docs"
Requires-Dist: sphinx-copybutton>=0.5.0; extra == "docs"
Requires-Dist: myst-parser>=1.0.0; extra == "docs"
Requires-Dist: sphinx-autobuild>=2021.3.14; extra == "docs"
Requires-Dist: linkify-it-py>=2.0.0; extra == "docs"
Dynamic: author
Dynamic: home-page
Dynamic: license-file
Dynamic: requires-python
